pytest_eradicate.py
pytest_eradicate-0.0.5.dist-info/METADATA
pytest_eradicate-0.0.5.dist-info/WHEEL
pytest_eradicate-0.0.5.dist-info/entry_points.txt
pytest_eradicate-0.0.5.dist-info/top_level.txt
pytest_eradicate-0.0.5.dist-info/RECORD
