Metadata-Version: 2.1
Name: pytest-eradicate
Version: 0.0.5
Summary: pytest plugin to check for commented out code
Home-page: https://github.com/aequitas/pytest-eradicate
Author: Johan Bloemberg
Author-email: github@ijohan.nl
License: MIT license
Platform: UNKNOWN
Classifier: Programming Language :: Python
Classifier: Programming Language :: Python :: 2.7
Classifier: Programming Language :: Python :: 3.8
Requires-Dist: pytest-cache
Requires-Dist: pytest (>=2.4.2)
Requires-Dist: eradicate
